geofactory/__init__.py
geofactory-0.0.2.dist-info/LICENSE
geofactory-0.0.2.dist-info/METADATA
geofactory-0.0.2.dist-info/WHEEL
geofactory-0.0.2.dist-info/top_level.txt
geofactory-0.0.2.dist-info/RECORD
