Metadata-Version: 2.1
Name: geofactory
Version: 0.0.2
Summary: A simple geojson provider for faker
Home-page: https://github.com/scook12/geofactory
Author: Samuel Cook
Author-email: rigdoncook@gmail.com
License: UNKNOWN
Platform: UNKNOWN
Classifier: Programming Language :: Python :: 3
Classifier: License :: OSI Approved :: MIT License
Classifier: Operating System :: OS Independent
Requires-Python: >=3.6
